odoo/addons/website_js_below_the_fold/README.rst
odoo/addons/website_js_below_the_fold/__init__.py
odoo/addons/website_js_below_the_fold/__manifest__.py
odoo/addons/website_js_below_the_fold/i18n/ca.po
odoo/addons/website_js_below_the_fold/i18n/es.po
odoo/addons/website_js_below_the_fold/i18n/fr.po
odoo/addons/website_js_below_the_fold/i18n/it.po
odoo/addons/website_js_below_the_fold/i18n/pt_BR.po
odoo/addons/website_js_below_the_fold/i18n/website_js_below_the_fold.pot
odoo/addons/website_js_below_the_fold/readme/CONTRIBUTORS.rst
odoo/addons/website_js_below_the_fold/readme/DESCRIPTION.rst
odoo/addons/website_js_below_the_fold/readme/USAGE.rst
odoo/addons/website_js_below_the_fold/static/description/icon.png
odoo/addons/website_js_below_the_fold/static/description/index.html
odoo/addons/website_js_below_the_fold/templates/website_js_below_the_fold.xml
odoo12_addon_website_js_below_the_fold-12.0.1.0.0.99.dev15.dist-info/METADATA
odoo12_addon_website_js_below_the_fold-12.0.1.0.0.99.dev15.dist-info/WHEEL
odoo12_addon_website_js_below_the_fold-12.0.1.0.0.99.dev15.dist-info/top_level.txt
odoo12_addon_website_js_below_the_fold-12.0.1.0.0.99.dev15.dist-info/RECORD
