Metadata-Version: 2.1
Name: odoo12-addon-website-js-below-the-fold
Version: 12.0.1.0.0.99.dev15
Summary: This module moves Javascript assets to the bottom of the page (below the fold)
Home-page: https://github.com/OCA/website
Author: Onestein, Odoo Community Association (OCA)
Author-email: support@odoo-community.org
License: AGPL-3
Platform: UNKNOWN
Classifier: Programming Language :: Python
Classifier: Framework :: Odoo
Classifier: Framework :: Odoo :: 12.0
Classifier: License :: OSI Approved :: GNU Affero General Public License v3
Requires-Python: >=3.5
Requires-Dist: odoo <12.1dev,>=12.0a
